zwergetl/components/s3/s3copyfiles.py
zwergetl/components/s3/s3copyfilesdirect.py
zwergetl/connections/s3/s3conn.py
zwergetl_components_aws_s3-0.1.11.dist-info/licenses/LICENSE.txt
zwergetl_components_aws_s3-0.1.11.dist-info/METADATA
zwergetl_components_aws_s3-0.1.11.dist-info/WHEEL
zwergetl_components_aws_s3-0.1.11.dist-info/top_level.txt
zwergetl_components_aws_s3-0.1.11.dist-info/RECORD
