Metadata-Version: 2.4
Name: zwergetl-components-aws-s3
Version: 0.1.11
Summary: ZwergETL components for AWS s3
Maintainer: dxdataworks
Requires-Python: >=3.6
License-File: LICENSE.txt
Requires-Dist: zwergetl-engine>=0.1.11
Requires-Dist: boto3>=1.37.23
Dynamic: license-file
